pyjazzclient/__init__.py
pyjazzclient/exceptions.py
pyjazzclient/jazzartifact.py
pyjazzclient/jazzclient.py
pyjazzclient/testcase.py
pyjazzclient-0.0.1.dist-info/METADATA
pyjazzclient-0.0.1.dist-info/WHEEL
pyjazzclient-0.0.1.dist-info/top_level.txt
pyjazzclient-0.0.1.dist-info/RECORD
