Metadata-Version: 2.1
Name: pyjazzclient
Version: 0.0.1
Summary: Python package for interacting with IBM Jazz
Home-page: https://github.com/gnomerspell/pyjazzclient
Author: Steve Wallace
Author-email: gnomerspell@gmail.com
License: UNKNOWN
Project-URL: Issues, https://github.com/gnomerspell/pyjazzclient/issues
Platform: UNKNOWN
Classifier: Development Status :: 1 - Planning
Classifier: Programming Language :: Python :: 3
Classifier: License :: OSI Approved :: MIT License
Classifier: Operating System :: OS Independent
Requires-Python: >=3.5
Requires-Dist: requests
